<?xml version="1.0"?>
<cena version="0.8.1"><result judgetime="43296.7396210648"><problem title="count" filename="count.cpp" status="1" hash="297880459" detail=""><testcase status="7" exitcode="0" detail="" time="0" memory="452" score="10"/><testcase status="7" exitcode="0" detail="" time="0" memory="448" score="10"/><testcase status="7" exitcode="0" detail="" time="0" memory="444" score="10"/><testcase status="7" exitcode="0" detail="" time="0.01" memory="444" score="10"/><testcase status="7" exitcode="0" detail="" time="0" memory="448" score="10"/><testcase status="7" exitcode="0" detail="" time="0" memory="452" score="10"/><testcase status="7" exitcode="0" detail="" time="0" memory="448" score="10"/><testcase status="7" exitcode="0" detail="" time="0" memory="448" score="10"/><testcase status="7" exitcode="0" detail="" time="0" memory="448" score="10"/><testcase status="7" exitcode="0" detail="" time="0" memory="452" score="10"/></problem><problem title="max" filename="max.cpp" status="1" hash="3822718179" detail=""><testcase status="7" exitcode="0" detail="" time="0" memory="1228" score="10"/><testcase status="7" exitcode="0" detail="" time="0" memory="1228" score="10"/><testcase status="7" exitcode="0" detail="" time="0" memory="1236" score="10"/><testcase status="7" exitcode="0" detail="" time="0" memory="1232" score="10"/><testcase status="7" exitcode="0" detail="" time="0" memory="1236" score="10"/><testcase status="7" exitcode="0" detail="" time="0.04" memory="1232" score="10"/><testcase status="7" exitcode="0" detail="" time="0.04" memory="1232" score="10"/><testcase status="7" exitcode="0" detail="" time="0.06" memory="1236" score="10"/><testcase status="7" exitcode="0" detail="" time="0.04" memory="1236" score="10"/><testcase status="7" exitcode="0" detail="" time="0.06" memory="1232" score="10"/></problem><problem title="cover" filename="cover.cpp" status="1" hash="1892483637" detail=""><testcase status="7" exitcode="0" detail="" time="0.09" memory="1620" score="10"/><testcase status="7" exitcode="0" detail="" time="0.1" memory="1624" score="10"/><testcase status="7" exitcode="0" detail="" time="0.1" memory="1624" score="10"/><testcase status="3" exitcode="1" detail="" time="1.0595348" memory="1620" score="0"/><testcase status="3" exitcode="1" detail="" time="1.0273578" memory="1620" score="0"/><testcase status="3" exitcode="1" detail="" time="1.0140065" memory="1620" score="0"/><testcase status="3" exitcode="1" detail="" time="1.0388091" memory="1932" score="0"/><testcase status="3" exitcode="1" detail="" time="1.0078573" memory="1932" score="0"/><testcase status="3" exitcode="1" detail="" time="1.2121363" memory="1968" score="0"/><testcase status="3" exitcode="1" detail="" time="1.1974659" memory="1964" score="0"/></problem></result></cena>
